[

  { "slno": 1		,"name": "RANJIT DEY",					"age": 42	,"contactno": "9477479862","bloodgroup": "AB+",		"address": "BARRACKPUR",								"donationdate": "14-01-2017","venue": "VIVIDISHANANDA SEVA KENDRA ,SODEPUR"},
  { "slno": 2		,"name": "SUBHANKAR BERA",				"age": 20	,"contactno": "8013126170","bloodgroup": "AB+",		"address": "SHYAMNAGAR",								"donationdate": "14-01-2017","venue": "VIVIDISHANANDA SEVA KENDRA ,SODEPUR"},
  { "slno": 3		,"name": "MONITA ORAN",					"age": 18	,"contactno": "9007964638","bloodgroup": "AB+",		"address": "CHAPDANI",									"donationdate": "14-01-2017","venue": "VIVIDISHANANDA SEVA KENDRA ,SODEPUR"},
  { "slno": 4		,"name": "RAHUL CHAKRABORTY",			"age": 23	,"contactno": "9230248019","bloodgroup": "AB+",		"address": "BARASAT",									"donationdate": "14-01-2017","venue": "VIVIDISHANANDA SEVA KENDRA ,SODEPUR"},
  { "slno": 5		,"name": "BISWAJIT ACHARYA",			"age": 21	,"contactno": "8479980061","bloodgroup": "AB+",		"address": "SHYAMNAGAR",								"donationdate": "14-01-2017","venue": "VIVIDISHANANDA SEVA KENDRA ,SODEPUR"},
  { "slno": 6		,"name": "KIRAN KUMARI SAHANI",			"age": 26	,"contactno": "9331336789","bloodgroup": "AB+",		"address": "DUMDUM",									"donationdate": "14-01-2017","venue": "VIVIDISHANANDA SEVA KENDRA ,SODEPUR"},
  { "slno": 7		,"name": "SWARNENDU GANGULY",			"age": 25	,"contactno": "9748804973","bloodgroup": "AB+",		"address": "SODEPUR",									"donationdate": "14-01-2017","venue": "VIVIDISHANANDA SEVA KENDRA ,SODEPUR"},
  { "slno": 8		,"name": "RIMPA DAS",					"age": 19	,"contactno": "8647090844","bloodgroup": "O+",		"address": "NAIHATI",									"donationdate": "14-01-2017","venue": "VIVIDISHANANDA SEVA KENDRA ,SODEPUR"},
  { "slno": 9		,"name": "MADHURI SHAW",				"age": 20	,"contactno": "9038852101","bloodgroup": "O+",		"address": "CHAPDANI",									"donationdate": "14-01-2017","venue": "VIVIDISHANANDA SEVA KENDRA ,SODEPUR"},
  { "slno": 10		,"name": "TUHIN DAS",					"age": 21	,"contactno": "9836665778","bloodgroup": "O+",		"address": "BARASAT",									"donationdate": "14-01-2017","venue": "VIVIDISHANANDA SEVA KENDRA ,SODEPUR"},
  { "slno": 11		,"name": "AJAY MRIDHA",					"age": 20	,"contactno": "9733190794","bloodgroup": "O+",		"address": "NADIA",										"donationdate": "14-01-2017","venue": "VIVIDISHANANDA SEVA KENDRA ,SODEPUR"},
  { "slno": 12		,"name": "NAJMUL HUDA",					"age": 20	,"contactno": "9647081104","bloodgroup": "O+",		"address": "MALDA",										"donationdate": "14-01-2017","venue": "VIVIDISHANANDA SEVA KENDRA ,SODEPUR"},
  { "slno": 13		,"name": "SUSHANTA DHAR",				"age": 35	,"contactno": "9883641195","bloodgroup": "O+",		"address": "N 24 PGS",									"donationdate": "14-01-2017","venue": "VIVIDISHANANDA SEVA KENDRA ,SODEPUR"},
  { "slno": 14		,"name": "ABHIMAN BISWAS",				"age": 31	,"contactno": "9903550810","bloodgroup": "O+",		"address": "BARRACKPORE",								"donationdate": "14-01-2017","venue": "VIVIDISHANANDA SEVA KENDRA ,SODEPUR"},
  { "slno": 15		,"name": "LAKSHMAN RAKSHIT",			"age": 30	,"contactno": "9038108081","bloodgroup": "O+",		"address": "BARRACKPORE",								"donationdate": "14-01-2017","venue": "VIVIDISHANANDA SEVA KENDRA ,SODEPUR"},
  { "slno": 16		,"name": "MAUSHUMI BALA",				"age": 19	,"contactno": "7687059800","bloodgroup": "O+",		"address": "SODPUR",									"donationdate": "14-01-2017","venue": "VIVIDISHANANDA SEVA KENDRA ,SODEPUR"},
  { "slno": 17		,"name": "BUDDHADEB RUIDAS",			"age": 21	,"contactno": "7098308607","bloodgroup": "O+",		"address": "BASIRHAT",									"donationdate": "14-01-2017","venue": "VIVIDISHANANDA SEVA KENDRA ,SODEPUR"},
  { "slno": 18		,"name": "RINKU MONDAL",				"age": 24	,"contactno": "9775370555","bloodgroup": "O+",		"address": "SHIMURALI",									"donationdate": "14-01-2017","venue": "VIVIDISHANANDA SEVA KENDRA ,SODEPUR"},
  { "slno": 19		,"name": "ABHIJEET SAHA",				"age": 18	,"contactno": "9804541502","bloodgroup": "O+",		"address": "NAIHATI",									"donationdate": "14-01-2017","venue": "VIVIDISHANANDA SEVA KENDRA ,SODEPUR"},
  { "slno": 20		,"name": "SUBHAJEET ADHIKARI",			"age": 19	,"contactno": "9038851967","bloodgroup": "O+",		"address": "NAIHATI",									"donationdate": "14-01-2017","venue": "VIVIDISHANANDA SEVA KENDRA ,SODEPUR"},
  { "slno": 21		,"name": "ASHIS DAS",					"age": 28	,"contactno": "9903397836","bloodgroup": "O+",		"address": "BARRACKPORE",								"donationdate": "14-01-2017","venue": "VIVIDISHANANDA SEVA KENDRA ,SODEPUR"},
  { "slno": 22		,"name": "SATYAJIT RAJAK",				"age": 30	,"contactno": "9477479862","bloodgroup": "O+",		"address": "BARRACKPORE",								"donationdate": "14-01-2017","venue": "VIVIDISHANANDA SEVA KENDRA ,SODEPUR"},
  { "slno": 23		,"name": "SUBHANKAR NANDY",				"age": 18	,"contactno": "0000000000","bloodgroup": "O+",		"address": "",											"donationdate": "14-01-2017","venue": "VIVIDISHANANDA SEVA KENDRA ,SODEPUR"},
  { "slno": 24		,"name": "SUBHAJIT SINHA",				"age": 32	,"contactno": "0000000000","bloodgroup": "O+",		"address": "",											"donationdate": "14-01-2017","venue": "VIVIDISHANANDA SEVA KENDRA ,SODEPUR"},
  { "slno": 25		,"name": "BIDHAN HAWLADAR",				"age": 22	,"contactno": "8276902404","bloodgroup": "O+",		"address": "BARRACKPORE",								"donationdate": "14-01-2017","venue": "VIVIDISHANANDA SEVA KENDRA ,SODEPUR"},
  { "slno": 26		,"name": "PARTHA SADHUKHAN",			"age": 35	,"contactno": "9804823376","bloodgroup": "O+",		"address": "BARRACKPORE",								"donationdate": "14-01-2017","venue": "VIVIDISHANANDA SEVA KENDRA ,SODEPUR"},
  { "slno": 27		,"name": "SNEHA SHAW",					"age": 27	,"contactno": "9163597081","bloodgroup": "O+",		"address": "BARRACKPORE",								"donationdate": "14-01-2017","venue": "VIVIDISHANANDA SEVA KENDRA ,SODEPUR"},
  { "slno": 28		,"name": "GOPAL CHANDRA DHAR",			"age": 33	,"contactno": "9903990824","bloodgroup": "O+",		"address": "BARRACKPORE",								"donationdate": "14-01-2017","venue": "VIVIDISHANANDA SEVA KENDRA ,SODEPUR"},
  { "slno": 29		,"name": "JAYANKUR GHOSH",				"age": 40	,"contactno": "9331136789","bloodgroup": "O+",		"address": "Sodepur",									"donationdate": "14-01-2017","venue": "VIVIDISHANANDA SEVA KENDRA ,SODEPUR"},
  { "slno": 30		,"name": "SHIBU DAS",					"age": 39	,"contactno": "9038092396","bloodgroup": "B+",		"address": "PALTA",										"donationdate": "14-01-2017","venue": "VIVIDISHANANDA SEVA KENDRA ,SODEPUR"},
  { "slno": 31		,"name": "TAMAL SARKAR",				"age": 31	,"contactno": "9051143655","bloodgroup": "B+",		"address": "BARRACKPORE",								"donationdate": "14-01-2017","venue": "VIVIDISHANANDA SEVA KENDRA ,SODEPUR"},
  { "slno": 32		,"name": "NILOY SARKAR",				"age": 33	,"contactno": "9836304396","bloodgroup": "B+",		"address": "BARRACKPORE",								"donationdate": "14-01-2017","venue": "VIVIDISHANANDA SEVA KENDRA ,SODEPUR"},
  { "slno": 33		,"name": "MANISHA BHAGAT",				"age": 20	,"contactno": "7890688589","bloodgroup": "B+",		"address": "ICHHAPUR",									"donationdate": "14-01-2017","venue": "VIVIDISHANANDA SEVA KENDRA ,SODEPUR"},
  { "slno": 34		,"name": "SUSHMITA PAUL",				"age": 20	,"contactno": "8276879419","bloodgroup": "B+",		"address": "SHYAMNAGAR",								"donationdate": "14-01-2017","venue": "VIVIDISHANANDA SEVA KENDRA ,SODEPUR"},
  { "slno": 35		,"name": "PRASHANTA SAMANTA",			"age": 24	,"contactno": "9062742155","bloodgroup": "B+",		"address": "BARASAT",									"donationdate": "14-01-2017","venue": "VIVIDISHANANDA SEVA KENDRA ,SODEPUR"},
  { "slno": 36		,"name": "SANDEEP MONDAL",				"age": 22	,"contactno": "8759732770","bloodgroup": "B+",		"address": "S 24 PGS",									"donationdate": "14-01-2017","venue": "VIVIDISHANANDA SEVA KENDRA ,SODEPUR"},
  { "slno": 37		,"name": "BIDESH SARDAR",				"age": 19	,"contactno": "9564813543","bloodgroup": "B+",		"address": "BASHIRHAT"									"donationdate": "14-01-2017","venue": "VIVIDISHANANDA SEVA KENDRA ,SODEPUR"},
  { "slno": 38		,"name": "RAJU CHAKRABORTY",			"age": 20	,"contactno": "8514962714","bloodgroup": "B+",		"address": "N 24 PGS",									"donationdate": "14-01-2017","venue": "VIVIDISHANANDA SEVA KENDRA ,SODEPUR"},
  { "slno": 39		,"name": "SANJAY MISHRA",				"age": 23	,"contactno": "8240074295","bloodgroup": "B+",		"address": "NEW TOWN",									"donationdate": "14-01-2017","venue": "VIVIDISHANANDA SEVA KENDRA ,SODEPUR"},
  { "slno": 40		,"name": "BISWAJIT DAS",				"age": 25	,"contactno": "9832403590","bloodgroup": "B+",		"address": "BASIRHAT",									"donationdate": "14-01-2017","venue": "VIVIDISHANANDA SEVA KENDRA ,SODEPUR"},
  { "slno": 41		,"name": "RAMKRISHNA PAUL",				"age": 20	,"contactno": "9091682288","bloodgroup": "B+",		"address": "BASIRHAT",									"donationdate": "14-01-2017","venue": "VIVIDISHANANDA SEVA KENDRA ,SODEPUR"},
  { "slno": 42		,"name": "SANDIPTA BHATTACHARJEE",		"age": 18	,"contactno": "8981913608","bloodgroup": "B+",		"address": "NAIHATI",									"donationdate": "14-01-2017","venue": "VIVIDISHANANDA SEVA KENDRA ,SODEPUR"},
  { "slno": 43		,"name": "JAYANTA DAS",					"age": 32	,"contactno": "9331207287","bloodgroup": "B+",		"address": "SODEPUR",									"donationdate": "14-01-2017","venue": "VIVIDISHANANDA SEVA KENDRA ,SODEPUR"},
  { "slno": 44		,"name": "VIVEK KR. SHRIVASTAVA",		"age": 23	,"contactno": "9038413740","bloodgroup": "B+",		"address": "KOLKATA",									"donationdate": "14-01-2017","venue": "VIVIDISHANANDA SEVA KENDRA ,SODEPUR"},
  { "slno": 45		,"name": "LABANI CHOWDHURY",			"age": 20	,"contactno": "9038576217","bloodgroup": "B+",		"address": "KHARDAH",									"donationdate": "14-01-2017","venue": "VIVIDISHANANDA SEVA KENDRA ,SODEPUR"},
  { "slno": 46		,"name": "PARTHA DAS",					"age": 30	,"contactno": "9681841433","bloodgroup": "B+",		"address": "SHYAMNAGAR"									"donationdate": "14-01-2017","venue": "VIVIDISHANANDA SEVA KENDRA ,SODEPUR"},
  { "slno": 47		,"name": "SUMAN PAUL",					"age": 20	,"contactno": "0000000000","bloodgroup": "B+",		"address": "",											"donationdate": "14-01-2017","venue": "VIVIDISHANANDA SEVA KENDRA ,SODEPUR"},
  { "slno": 48		,"name": "ANUSH PAUL",					"age": 22	,"contactno": "0000000000","bloodgroup": "B+",		"address": "",											"donationdate": "14-01-2017","venue": "VIVIDISHANANDA SEVA KENDRA ,SODEPUR"},
  { "slno": 49		,"name": "ASHMIT BHANJA",				"age": 19	,"contactno": "0000000000","bloodgroup": "B+",		"address": "",											"donationdate": "14-01-2017","venue": "VIVIDISHANANDA SEVA KENDRA ,SODEPUR"},
  { "slno": 50		,"name": "Subrata Paul",				"age": 26	,"contactno": "9681383164","bloodgroup": "B+",		"address": "Barrackpore",								"donationdate": "14-01-2017","venue": "VIVIDISHANANDA SEVA KENDRA ,SODEPUR"},
  { "slno": 51		,"name": "RAM ADHIKARI",				"age": 40	,"contactno": "9775458899","bloodgroup": "B+",		"address": "Barrackpore",								"donationdate": "14-01-2017","venue": "VIVIDISHANANDA SEVA KENDRA ,SODEPUR"},
  { "slno": 52		,"name": "Prakash Shaw",				"age": 34	,"contactno": "9163597567","bloodgroup": "B+",		"address": "Barrackpore",								"donationdate": "14-01-2017","venue": "VIVIDISHANANDA SEVA KENDRA ,SODEPUR"},
  { "slno": 53		,"name": "BIPLAB RUI DAS",				"age": 20	,"contactno": "8621848446","bloodgroup": "A+",		"address": "SHYAMNAGAR",								"donationdate": "14-01-2017","venue": "VIVIDISHANANDA SEVA KENDRA ,SODEPUR"},
  { "slno": 54		,"name": "SUJAY DEBNATH",				"age": 19	,"contactno": "8514882681","bloodgroup": "A+",		"address": "N 24 PGS",									"donationdate": "14-01-2017","venue": "VIVIDISHANANDA SEVA KENDRA ,SODEPUR"},
  { "slno": 55		,"name": "RITUPARNA MONDAL",			"age": 20	,"contactno": "9547799941","bloodgroup": "A+",		"address": "SIMURALI",									"donationdate": "14-01-2017","venue": "VIVIDISHANANDA SEVA KENDRA ,SODEPUR"},
  { "slno": 56		,"name": "TIYASHA DEB",					"age": 18	,"contactno": "9674790826","bloodgroup": "A+",		"address": "NAIHATI",									"donationdate": "14-01-2017","venue": "VIVIDISHANANDA SEVA KENDRA ,SODEPUR"},
  { "slno": 57		,"name": "AMRIT BALA",					"age": 22	,"contactno": "8282956313","bloodgroup": "A+",		"address": "PALTA",										"donationdate": "14-01-2017","venue": "VIVIDISHANANDA SEVA KENDRA ,SODEPUR"},
  { "slno": 58		,"name": "Tilon Ghorui",				"age": 23	,"contactno": "9564183152","bloodgroup": "A+",		"address": "Srirampur",									"donationdate": "14-01-2017","venue": "VIVIDISHANANDA SEVA KENDRA ,SODEPUR"},
  { "slno": 59		,"name": "Rajeswari Roy",				"age": 20	,"contactno": "9062108676","bloodgroup": "A+",		"address": "Shyamnagar",								"donationdate": "14-01-2017","venue": "VIVIDISHANANDA SEVA KENDRA ,SODEPUR"},
  { "slno": 60		,"name": "Santu Das",					"age": 24	,"contactno": "8961432752","bloodgroup": "A+",		"address": "Naihati",									"donationdate": "14-01-2017","venue": "VIVIDISHANANDA SEVA KENDRA ,SODEPUR"},
  { "slno": 61		,"name": "Shubhankar Saha",				"age": 25	,"contactno": "9883739770","bloodgroup": "A+",		"address": "Sodepur",									"donationdate": "14-01-2017","venue": "VIVIDISHANANDA SEVA KENDRA ,SODEPUR"},
  { "slno": 62		,"name": "Saibal Das",					"age": 35	,"contactno": "8001194815","bloodgroup": "A+",		"address": "Barrackpore",								"donationdate": "14-01-2017","venue": "VIVIDISHANANDA SEVA KENDRA ,SODEPUR"},
  
  { "slno": 63		,"name": "Sumeet Sanehl",				"age": 29	,"contactno": "9831855797","bloodgroup": "O+",		"address": "",											"donationdate": "24-06-2017","venue": "MISSION OF MERCCY HOSPITAL, 125/1 Park Street, Kolkata-700017"},
  { "slno": 64		,"name": "Debaratti Bose",				"age": 27	,"contactno": "8972890974","bloodgroup": "B+",		"address": "Narayanpur, Kol- 136",						"donationdate": "24-06-2017","venue": "MISSION OF MERCCY HOSPITAL, 125/1 Park Street, Kolkata-700017"},
  { "slno": 65		,"name": "Sourav Adhikari",				"age": 25	,"contactno": "8583916448","bloodgroup": "O+",		"address": "Barrackpur",								"donationdate": "24-06-2017","venue": "MISSION OF MERCCY HOSPITAL, 125/1 Park Street, Kolkata-700017"},
  { "slno": 66		,"name": "Tanmoy Sett",					"age": 30	,"contactno": "9002788472","bloodgroup": "A+",		"address": "Narayanpur, Kol- 136",						"donationdate": "24-06-2017","venue": "MISSION OF MERCCY HOSPITAL, 125/1 Park Street, Kolkata-700017"},
  { "slno": 67		,"name": "Ambika Thapa",				"age": 28	,"contactno": "8336854257","bloodgroup": "B+",		"address": "E-15, Shantaneer, GLT Road.",				"donationdate": "24-06-2017","venue": "MISSION OF MERCCY HOSPITAL, 125/1 Park Street, Kolkata-700017"},
  { "slno": 68		,"name": "Debapriya Ghosh",				"age": 28	,"contactno": "9836397890","bloodgroup": "O+",		"address": "Brliaghata, Jora Mandir",					"donationdate": "24-06-2017","venue": "MISSION OF MERCCY HOSPITAL, 125/1 Park Street, Kolkata-700017"},
  { "slno": 69		,"name": "Santanu Das",					"age": 37	,"contactno": "9836699832","bloodgroup": "A+",		"address": "shyam Vihar, Kol-59",						"donationdate": "24-06-2017","venue": "MISSION OF MERCCY HOSPITAL, 125/1 Park Street, Kolkata-700017"},
  { "slno": 70		,"name": "Bidhan Ch. Hawladar",			"age": 23	,"contactno": "9088446004","bloodgroup": "O+",		"address": "Barrackpur",								"donationdate": "24-06-2017","venue": "MISSION OF MERCCY HOSPITAL, 125/1 Park Street, Kolkata-700017"},
  { "slno": 71		,"name": "Tanmoy Nath",					"age": 29	,"contactno": "9836626965","bloodgroup": "A+",		"address": "Subhasnagar",								"donationdate": "24-06-2017","venue": "MISSION OF MERCCY HOSPITAL, 125/1 Park Street, Kolkata-700017"},
  { "slno": 72		,"name": "Rajesh Prasad",				"age": 42	,"contactno": "9051600514","bloodgroup": "B+",		"address": "Subhasnagar",								"donationdate": "24-06-2017","venue": "MISSION OF MERCCY HOSPITAL, 125/1 Park Street, Kolkata-700017"},
  { "slno": 73		,"name": "Sampriya Banerjee",			"age": 34	,"contactno": "9674141161","bloodgroup": "O+",		"address": "Subhasnagar",								"donationdate": "24-06-2017","venue": "MISSION OF MERCCY HOSPITAL, 125/1 Park Street, Kolkata-700017"},
  { "slno": 74		,"name": "Shibu Das",					"age": 40	,"contactno": "9038092396","bloodgroup": "B+",		"address": "24/A, Kalianibas, BKP",						"donationdate": "24-06-2017","venue": "MISSION OF MERCCY HOSPITAL, 125/1 Park Street, Kolkata-700017"},
  { "slno": 75		,"name": "Sandeed Baral",				"age": 32	,"contactno": "9051660495","bloodgroup": "O+",		"address": "69/9, R.N.Huha Rd, Nager Bazar, Dum Dum",	"donationdate": "24-06-2017","venue": "MISSION OF MERCCY HOSPITAL, 125/1 Park Street, Kolkata-700017"},
  { "slno": 76		,"name": "Sourav Mondal",				"age": 30	,"contactno": "9051255770","bloodgroup": "O+",		"address": "B-7, Gitaanjali Park, Ariadaha",			"donationdate": "24-06-2017","venue": "MISSION OF MERCCY HOSPITAL, 125/1 Park Street, Kolkata-700017"},
  { "slno": 77		,"name": "Arindam Bagchi",				"age": 24	,"contactno": "8981614702","bloodgroup": "B+",		"address": "44/1, Ramlal Agarwal Lane, Kol - 50",		"donationdate": "24-06-2017","venue": "MISSION OF MERCCY HOSPITAL, 125/1 Park Street, Kolkata-700017"},
  { "slno": 78		,"name": "Raja Kar",					"age": 48	,"contactno": "8582907723","bloodgroup": "AB+",		"address": "L/67, Naktala, Kolkata.",					"donationdate": "24-06-2017","venue": "MISSION OF MERCCY HOSPITAL, 125/1 Park Street, Kolkata-700017"},
  { "slno": 79		,"name": "Saurav Chandra",				"age": 31	,"contactno": "8017774875","bloodgroup": "A+",		"address": "Keshtapur, Kol-102",						"donationdate": "24-06-2017","venue": "MISSION OF MERCCY HOSPITAL, 125/1 Park Street, Kolkata-700017"},
  { "slno": 80		,"name": "Jaya Saha",					"age": 29	,"contactno": "9477432254","bloodgroup": "O+",		"address": "Keshtapur, Kol-102",						"donationdate": "24-06-2017","venue": "MISSION OF MERCCY HOSPITAL, 125/1 Park Street, Kolkata-700017"},
  { "slno": 81		,"name": "Sukumar Patra",				"age": 35	,"contactno": "9674631846","bloodgroup": "O+",		"address": "8, Baguhati 3rd Lane,DumDum, Kol-28",		"donationdate": "24-06-2017","venue": "MISSION OF MERCCY HOSPITAL, 125/1 Park Street, Kolkata-700017"},
  { "slno": 82		,"name": "Samik Basu",					"age": 28	,"contactno": "9143297717","bloodgroup": "B+",		"address": "Bibeknagar, Noapara,Barasat, Kol - 125",	"donationdate": "24-06-2017","venue": "MISSION OF MERCCY HOSPITAL, 125/1 Park Street, Kolkata-700017"},
  { "slno": 83		,"name": "Santanu Chakraborty",			"age": 46	,"contactno": "9830774479","bloodgroup": "A+",		"address": "55, SHK Basu Sarani, Basusree Appt.",		"donationdate": "24-06-2017","venue": "MISSION OF MERCCY HOSPITAL, 125/1 Park Street, Kolkata-700017"},
  { "slno": 84		,"name": "Trishit Kr. Bera",			"age": 30	,"contactno": "9007868880","bloodgroup": "O+",		"address": "6/34, Bijaygarh, Kol - 32",					"donationdate": "24-06-2017","venue": "MISSION OF MERCCY HOSPITAL, 125/1 Park Street, Kolkata-700017"},
  { "slno": 85		,"name": "Upen Patra",					"age": 26	,"contactno": "9674742567","bloodgroup": "B+",		"address": "Newtown",									"donationdate": "24-06-2017","venue": "MISSION OF MERCCY HOSPITAL, 125/1 Park Street, Kolkata-700017"},
  { "slno": 86		,"name": "Ruma Chakraborty",			"age": 46	,"contactno": "9830016167","bloodgroup": "A-",		"address": "55, SHK Basu Sarani, Basusree Appt.",		"donationdate": "24-06-2017","venue": "MISSION OF MERCCY HOSPITAL, 125/1 Park Street, Kolkata-700017"},
  { "slno": 87		,"name": "Dr. D. Bandopadhyay",			"age": 31	,"contactno": "9830462486","bloodgroup": "O+",		"address": "CEQ 5/3, Ralla Doctors Colony, Kol- 713340","donationdate": "24-06-2017","venue": "MISSION OF MERCCY HOSPITAL, 125/1 Park Street, Kolkata-700017"},
  { "slno": 88		,"name": "Sushmita Mukherjee",			"age": 31	,"contactno": "8906156439","bloodgroup": "A+",		"address": "CEQ 5/3, Kol- 713340",						"donationdate": "24-06-2017","venue": "MISSION OF MERCCY HOSPITAL, 125/1 Park Street, Kolkata-700017"},
  { "slno": 89		,"name": "Prakash Shaw",				"age": 36	,"contactno": "9163597567","bloodgroup": "B+",		"address": "Barrackpur",								"donationdate": "24-06-2017","venue": "MISSION OF MERCCY HOSPITAL, 125/1 Park Street, Kolkata-700017"},
  { "slno": 90		,"name": "Sujay Kr. Das",				"age": 34	,"contactno": "7003027404","bloodgroup": "B+",		"address": "Barrackpur",								"donationdate": "24-06-2017","venue": "MISSION OF MERCCY HOSPITAL, 125/1 Park Street, Kolkata-700017"},
  { "slno": 91		,"name": "Hamhir Biswas",				"age": 27	,"contactno": "9874370273","bloodgroup": "AB+",		"address": "Sruti Appt. B.P. Road, Kol-28",				"donationdate": "24-06-2017","venue": "MISSION OF MERCCY HOSPITAL, 125/1 Park Street, Kolkata-700017"},
  { "slno": 92		,"name": "Tamaz Chakraborty",			"age": 27	,"contactno": "8670310621","bloodgroup": "O+",		"address": "Bongawn",									"donationdate": "24-06-2017","venue": "MISSION OF MERCCY HOSPITAL, 125/1 Park Street, Kolkata-700017"},
  { "slno": 93		,"name": "Shuvrajit Kundu",				"age": 33	,"contactno": "8420240585","bloodgroup": "O+",		"address": "56/2B, Ramdulal Sarani St.   Kol- 6",		"donationdate": "24-06-2017","venue": "MISSION OF MERCCY HOSPITAL, 125/1 Park Street, Kolkata-700017"},
  { "slno": 94		,"name": "Kajal Manna",					"age": 18	,"contactno": "9647429607","bloodgroup": "AB+",		"address": "Hasnabad",									"donationdate": "24-06-2017","venue": "MISSION OF MERCCY HOSPITAL, 125/1 Park Street, Kolkata-700017"},
  { "slno": 95		,"name": "Nilanjan Chakraborty",		"age": 29	,"contactno": "9830658193","bloodgroup": "A+",		"address": "1/23, Suryanagar, Kol- 40",					"donationdate": "24-06-2017","venue": "MISSION OF MERCCY HOSPITAL, 125/1 Park Street, Kolkata-700017"},
  { "slno": 96		,"name": "Anirban Dey",					"age": 33	,"contactno": "9642465550","bloodgroup": "O+",		"address": "2/44A, Suryanagar, Kol- 40",				"donationdate": "24-06-2017","venue": "MISSION OF MERCCY HOSPITAL, 125/1 Park Street, Kolkata-700017"},
  { "slno": 97		,"name": "Somnath Basu",				"age": 62	,"contactno": "9674869085","bloodgroup": "O+",		"address": "89, Subhasnagar, Kol-65",					"donationdate": "24-06-2017","venue": "MISSION OF MERCCY HOSPITAL, 125/1 Park Street, Kolkata-700017"},
  { "slno": 98		,"name": "Chandraddip Saha",			"age": 27	,"contactno": "9883733290","bloodgroup": "A+",		"address": "180, Dakshin para Rd., Dumdum, Kol-28",		"donationdate": "24-06-2017","venue": "MISSION OF MERCCY HOSPITAL, 125/1 Park Street, Kolkata-700017"},
  { "slno": 99		,"name": "Saibal Das",					"age": 35	,"contactno": "8001194815","bloodgroup": "A+",		"address": "Barrackpur",								"donationdate": "24-06-2017","venue": "MISSION OF MERCCY HOSPITAL, 125/1 Park Street, Kolkata-700017"},
  { "slno": 100		,"name": "Kuntal Mondal",				"age": 25	,"contactno": "9681166630","bloodgroup": "B+",		"address": "Rajarhat, Newtown",							"donationdate": "24-06-2017","venue": "MISSION OF MERCCY HOSPITAL, 125/1 Park Street, Kolkata-700017"},
  { "slno": 101		,"name": "Ripan Dutta",					"age": 23	,"contactno": "8981780090","bloodgroup": "A+",		"address": "138, Subhashnagar, Dum Dum Cant.",			"donationdate": "24-06-2017","venue": "MISSION OF MERCCY HOSPITAL, 125/1 Park Street, Kolkata-700017"},
  { "slno": 102 	,"name": "Sayantani Das",				"age": 22	,"contactno": "8981071238","bloodgroup": "B+",		"address": "253, Vivekananda Road, Kol - 65",			"donationdate": "24-06-2017","venue": "MISSION OF MERCCY HOSPITAL, 125/1 Park Street, Kolkata-700017"},
  { "slno": 103		,"name": "Palash Ghosh",				"age": 21	,"contactno": "7908247363","bloodgroup": "O+",		"address": "Raidighi, Kol-743383",						"donationdate": "24-06-2017","venue": "MISSION OF MERCCY HOSPITAL, 125/1 Park Street, Kolkata-700017"},
  { "slno": 104		,"name": "Sujan Mistry",				"age": 26	,"contactno": "7872102662","bloodgroup": "B+",		"address": "Kalayachia, Diamond Harbour",				"donationdate": "24-06-2017","venue": "MISSION OF MERCCY HOSPITAL, 125/1 Park Street, Kolkata-700017"},
  { "slno": 105		,"name": "Satyajit Mondal",				"age": 24	,"contactno": "8768541323","bloodgroup": "A+",		"address": "Ustthi, Kol- 743609",						"donationdate": "24-06-2017","venue": "MISSION OF MERCCY HOSPITAL, 125/1 Park Street, Kolkata-700017"},
  { "slno": 106		,"name": "Soumayadip Ghosh",			"age": 18	,"contactno": "7998269699","bloodgroup": "O+",		"address": "Devoke, Mamudpur",							"donationdate": "24-06-2017","venue": "MISSION OF MERCCY HOSPITAL, 125/1 Park Street, Kolkata-700017"},
  { "slno": 107		,"name": "Nikhil Mondal",				"age": 19	,"contactno": "8647930465","bloodgroup": "O+",		"address": "Naihati",									"donationdate": "24-06-2017","venue": "MISSION OF MERCCY HOSPITAL, 125/1 Park Street, Kolkata-700017"},
  { "slno": 108		,"name": "Maloy Chakraborty",			"age": 21	,"contactno": "7501279570","bloodgroup": "AB+",		"address": "Diamond Harbour",							"donationdate": "24-06-2017","venue": "MISSION OF MERCCY HOSPITAL, 125/1 Park Street, Kolkata-700017"},
  { "slno": 109		,"name": "Partha Bhowmick",				"age": 35	,"contactno": "9831955285","bloodgroup": "A+",		"address": "Barrackpur",								"donationdate": "24-06-2017","venue": "MISSION OF MERCCY HOSPITAL, 125/1 Park Street, Kolkata-700017"},
  { "slno": 110		,"name": "Biswajit Acharya",			"age": 22	,"contactno": "8479980061","bloodgroup": "AB-",		"address": "Shyamnagar",								"donationdate": "24-06-2017","venue": "MISSION OF MERCCY HOSPITAL, 125/1 Park Street, Kolkata-700017"},
  { "slno": 111		,"name": "Santu Das",					"age": 25	,"contactno": "8961432752","bloodgroup": "A+",		"address": "Naihati",									"donationdate": "24-06-2017","venue": "MISSION OF MERCCY HOSPITAL, 125/1 Park Street, Kolkata-700017"},
  { "slno": 112		,"name": "Aparna Mallick",				"age": 22	,"contactno": "8100881244","bloodgroup": "O+",		"address": "Naihati",									"donationdate": "24-06-2017","venue": "MISSION OF MERCCY HOSPITAL, 125/1 Park Street, Kolkata-700017"},
  { "slno": 113		,"name": "Ram Ch. Adhikary",			"age": 41	,"contactno": "9775458899","bloodgroup": "AB+",		"address": "Barrackpur",								"donationdate": "24-06-2017","venue": "MISSION OF MERCCY HOSPITAL, 125/1 Park Street, Kolkata-700017"},
  { "slno": 114		,"name": "Nabanita Basu",				"age": 31	,"contactno": "9163818490","bloodgroup": "O+",		"address": "Naktala, Kol- 47",							"donationdate": "24-06-2017","venue": "MISSION OF MERCCY HOSPITAL, 125/1 Park Street, Kolkata-700017"},
  { "slno": 115		,"name": "Gopal Ch. Dhar",				"age": 35	,"contactno": "9903990824","bloodgroup": "O+",		"address": "Saraju Appt., Chandmari,East Rd., BKP",		"donationdate": "24-06-2017","venue": "MISSION OF MERCCY HOSPITAL, 125/1 Park Street, Kolkata-700017"},
  { "slno": 116		,"name": "Arunima Halder",				"age": 23	,"contactno": "8621036402","bloodgroup": "O+",		"address": "Barrackpur",								"donationdate": "24-06-2017","venue": "MISSION OF MERCCY HOSPITAL, 125/1 Park Street, Kolkata-700017"},
  { "slno": 117		,"name": "Dip Kr. Sarkar",				"age": 18	,"contactno": "9748064090","bloodgroup": "B+",		"address": "Shyamnagar",								"donationdate": "24-06-2017","venue": "MISSION OF MERCCY HOSPITAL, 125/1 Park Street, Kolkata-700017"},
  { "slno": 118		,"name": "Priyankar Mondal",			"age": 18	,"contactno": "8972285133","bloodgroup": "B+",		"address": "Karaibria, Ramnagar",						"donationdate": "24-06-2017","venue": "MISSION OF MERCCY HOSPITAL, 125/1 Park Street, Kolkata-700017"},
  { "slno": 119		,"name": "Kaushik Ray",					"age": 31	,"contactno": "9830372250","bloodgroup": "O+",		"address": "Naktala, Kol - 47",							"donationdate": "24-06-2017","venue": "MISSION OF MERCCY HOSPITAL, 125/1 Park Street, Kolkata-700017"},
  { "slno": 120		,"name": "Niloy Sarkar",				"age": 33	,"contactno": "9836304396","bloodgroup": "B+",		"address": "Barrackpur",								"donationdate": "24-06-2017","venue": "MISSION OF MERCCY HOSPITAL, 125/1 Park Street, Kolkata-700017"}


]